rafnix/__init__.py
rafnix/model.py
rafnix/predict.py
rafnix-0.1.0.dist-info/METADATA
rafnix-0.1.0.dist-info/WHEEL
rafnix-0.1.0.dist-info/top_level.txt
rafnix-0.1.0.dist-info/RECORD
