Metadata-Version: 2.1
Name: rafnix
Version: 0.1.0
Summary: A library for disease prediction using machine learning
Home-page: https://github.com/EmekaIwuagwu/rafnix
Author: Emeka Iwuagwu
Author-email: e.iwuagwu@hotmail.com
Classifier: Programming Language :: Python :: 3
Classifier: License :: OSI Approved :: MIT License
Classifier: Operating System :: OS Independent
Requires-Python: >=3.6
Requires-Dist: pandas
Requires-Dist: scikit-learn
